[
    {
        "id": "1137412",
        "name": "Gonzalo Camiruaga",
        "image": null,
        "dob": null,
        "nationality": null
    },
    {
        "id": "1137415",
        "name": "Pablo Silva",
        "image": null,
        "dob": null,
        "nationality": null
    },
    {
        "id": "566401",
        "name": "Marco Medina",
        "image": null,
        "dob": null,
        "nationality": null
    },
    {
        "id": "1137414",
        "name": "Frank Werner",
        "image": null,
        "dob": null,
        "nationality": null
    },
    {
        "id": "566399",
        "name": "Rodrigo Desriviers",
        "image": null,
        "dob": null,
        "nationality": "Chile"
    },
    {
        "id": "566301",
        "name": "Kilian du Couedic",
        "image": null,
        "dob": null,
        "nationality": "France"
    },
    {
        "id": "1137413",
        "name": "Luciano Barozzi",
        "image": null,
        "dob": null,
        "nationality": null
    },
    {
        "id": "566400",
        "name": "Paco Stuven",
        "image": null,
        "dob": null,
        "nationality": "Chile"
    },
    {
        "id": "1137416",
        "name": "Cote Chuki Astorquiza",
        "image": null,
        "dob": null,
        "nationality": null
    },
    {
        "id": "1137409",
        "name": "Giancarlo Stagno",
        "image": null,
        "dob": null,
        "nationality": null
    },
    {
        "id": "1206435",
        "name": "Giorgio Stagno Finger",
        "image": null,
        "dob": "1974-05-03",
        "nationality": "Chile"
    },
    {
        "id": "1206567",
        "name": "Raoul Reiner",
        "image": null,
        "dob": "1973-02-01",
        "nationality": "Germany"
    },
    {
        "id": "529958",
        "name": "Mariano Pecora",
        "image": null,
        "dob": null,
        "nationality": "Argentina"
    }
]