[
    {
        "id": "1437408",
        "name": "Dominica Osman",
        "image": "https://liveheats.com/images/5c7255a3-841b-4739-ad71-e775a22621fa.webp",
        "dob": "1999-03-29",
        "nationality": "Argentina"
    },
    {
        "id": "1206272",
        "name": "Noni Stuven",
        "image": "https://liveheats.com/images/3508d6f5-6a3d-487d-9e93-fc8394d5da62.webp",
        "dob": "2011-04-18",
        "nationality": "Chile"
    },
    {
        "id": "1247117",
        "name": "Cecilia Lopez del Rosso",
        "image": null,
        "dob": null,
        "nationality": null
    },
    {
        "id": "566392",
        "name": "Camila East",
        "image": null,
        "dob": null,
        "nationality": "Chile"
    },
    {
        "id": "1500082",
        "name": "Ursula Speiser",
        "image": null,
        "dob": null,
        "nationality": null
    }
]