[
    {
        "id": "820028",
        "name": "Coco Foveau",
        "image": "https://www.liveheats.com/images/4b3dbbe9-d76b-4c33-a9fc-802d45bdc46c.webp",
        "dob": "1999-06-21",
        "nationality": "France"
    },
    {
        "id": "820787",
        "name": "Maria Andres",
        "image": "https://liveheats.com/images/eaaa41d3-ff45-48a8-8d91-a8db68341c2e.webp",
        "dob": "1983-08-11",
        "nationality": "Spanish"
    },
    {
        "id": "1542069",
        "name": "Denise Blondet",
        "image": null,
        "dob": "1996-11-19",
        "nationality": "Peru"
    },
    {
        "id": "107339",
        "name": "Kaelyn Holmes",
        "image": "https://liveheats.com/images/45f265f9-dab8-4527-b58d-6b416ac20411.webp",
        "dob": "2007-01-19",
        "nationality": "Puerto Rico"
    }
]