[
    {
        "id": "1122464",
        "name": "Eilidh Sutherland",
        "image": null,
        "dob": null,
        "nationality": null
    },
    {
        "id": "1573703",
        "name": "Cori McFarlane",
        "image": null,
        "dob": null,
        "nationality": null
    },
    {
        "id": "1122462",
        "name": "Izzy Adcock",
        "image": null,
        "dob": null,
        "nationality": null
    },
    {
        "id": "1122461",
        "name": "Annika Loh",
        "image": null,
        "dob": null,
        "nationality": null
    },
    {
        "id": "1122460",
        "name": "Liath Campbell",
        "image": null,
        "dob": null,
        "nationality": null
    }
]